Verilog/PropSumGen/PSG.v
// PropSumGen to create P, Sum and G for CLA
module PSG(A, B, C, P_inv, G_inv, S);
    input A, B, C;
    output P_inv, G_inv, S;
    wire temp1;   

    nor n1(P_inv, A, B);
    nand n2(G_inv, A, B);
    xor x1(temp1, A, B);
    xor x2(S, temp1, C);

endmodule

Verilog/PropSumGen/PSG_tb.v
// Testbench for the PSG module
`timescale 1ns/1ps
`include "PSG.v"

module PSG_tb;
    reg A, B, C;
    wire P_inv, G_inv, S;

    PSG uut(.A(A), .B(B), .C(C), .P_inv(P_inv), .G_inv(G_inv), .S(S));

    initial begin
        $dumpfile("PSG_tb.vcd");
        $dumpvars(0, PSG_tb);

        A = 0; B = 0; C = 0; #10;
        A = 0; B = 0; C = 1; #10;
        A = 0; B = 1; C = 0; #10;
        A = 0; B = 1; C = 1; #10;
        A = 1; B = 0; C = 0; #10;
        A = 1; B = 0; C = 1; #10;
        A = 1; B = 1; C = 0; #10;
        A = 1; B = 1; C = 1; #10;

        $finish;
    end

endmodule

Verilog/PropSumGen/PSG_tb.vcd
$date
	Wed Nov 13 12:42:54 2024
$end
$version
	Icarus Verilog
$end
$timescale
	1ps
$end
$scope module PSG_tb $end
$var wire 1 ! S $end
$var wire 1 " P_inv $end
$var wire 1 # G_inv $end
$var reg 1 $ A $end
$var reg 1 % B $end
$var reg 1 & C $end
$scope module uut $end
$var wire 1 $ A $end
$var wire 1 % B $end
$var wire 1 & C $end
$var wire 1 # G_inv $end
$var wire 1 " P_inv $end
$var wire 1 ! S $end
$var wire 1 ' temp1 $end
$upscope $end
$upscope $end
$enddefinitions $end
$comment Show the parameter values. $end
$dumpall
$end
#0
$dumpvars
0'
0&
0%
0$
1#
1"
0!
$end
#10000
1!
1&
#20000
0"
1'
0&
1%
#30000
0!
1&
#40000
1!
0&
0%
1$
#50000
0!
1&
#60000
0#
0'
0&
1%
#70000
1!
1&
